hypothesis_openapi/__init__.py
hypothesis_openapi/_common.py
hypothesis_openapi/_serialize.py
hypothesis_openapi/_strategies.py
hypothesis_openapi/_types.py
hypothesis_openapi/_v2.py
hypothesis_openapi/_v3.py
hypothesis_openapi/py.typed
hypothesis_openapi-0.2.1.dist-info/METADATA
hypothesis_openapi-0.2.1.dist-info/WHEEL
hypothesis_openapi-0.2.1.dist-info/licenses/LICENSE
hypothesis_openapi-0.2.1.dist-info/RECORD
